<featureType>
  <id>FeatureTypeInfoImpl--1c23d84c:179a2d3b145:63e3</id>
  <name>Line_between_1y_and_2y</name>
  <nativeName>Line_geom_age</nativeName>
  <namespace>
    <id>NamespaceInfoImpl-65e80db7:1799edf6a0d:-7ffe</id>
  </namespace>
  <title>Line_geom_age</title>
  <keywords>
    <string>features</string>
    <string>Line_geom_age</string>
  </keywords>
  <nativeCRS class="projected">PROJCS[&quot;WGS84 / Google Mercator&quot;, &#xd;
  GEOGCS[&quot;WGS 84&quot;, &#xd;
    DATUM[&quot;World Geodetic System 1984&quot;, &#xd;
      SPHEROID[&quot;WGS 84&quot;, 6378137.0, 298.257223563, AUTHORITY[&quot;EPSG&quot;,&quot;7030&quot;]], &#xd;
      AUTHORITY[&quot;EPSG&quot;,&quot;6326&quot;]], &#xd;
    PRIMEM[&quot;Greenwich&quot;, 0.0, AUTHORITY[&quot;EPSG&quot;,&quot;8901&quot;]], &#xd;
    UNIT[&quot;degree&quot;, 0.017453292519943295], &#xd;
    AXIS[&quot;Longitude&quot;, EAST], &#xd;
    AXIS[&quot;Latitude&quot;, NORTH], &#xd;
    AUTHORITY[&quot;EPSG&quot;,&quot;4326&quot;]], &#xd;
  PROJECTION[&quot;Mercator_1SP&quot;], &#xd;
  PARAMETER[&quot;semi_minor&quot;, 6378137.0], &#xd;
  PARAMETER[&quot;latitude_of_origin&quot;, 0.0], &#xd;
  PARAMETER[&quot;central_meridian&quot;, 0.0], &#xd;
  PARAMETER[&quot;scale_factor&quot;, 1.0], &#xd;
  PARAMETER[&quot;false_easting&quot;, 0.0], &#xd;
  PARAMETER[&quot;false_northing&quot;, 0.0], &#xd;
  UNIT[&quot;m&quot;, 1.0], &#xd;
  AXIS[&quot;x&quot;, EAST], &#xd;
  AXIS[&quot;y&quot;, NORTH], &#xd;
  AUTHORITY[&quot;EPSG&quot;,&quot;900913&quot;]]</nativeCRS>
  <srs>EPSG:900913</srs>
  <nativeBoundingBox>
    <minx>-274800.734623986</minx>
    <maxx>1248422.50802758</maxx>
    <miny>4204069.18725979</miny>
    <maxy>5359622.22738192</maxy>
    <crs class="projected">EPSG:900913</crs>
  </nativeBoundingBox>
  <latLonBoundingBox>
    <minx>-2.4685769999999922</minx>
    <maxx>11.214770200000013</maxx>
    <miny>35.2951914</miny>
    <maxy>43.31225870000001</maxy>
    <crs>EPSG:4326</crs>
  </latLonBoundingBox>
  <projectionPolicy>FORCE_DECLARED</projectionPolicy>
  <enabled>true</enabled>
  <metadata>
    <entry key="cachingEnabled">false</entry>
  </metadata>
  <store class="dataStore">
    <id>DataStoreInfoImpl-2207362e:1799ee2cd49:-7fff</id>
  </store>
  <serviceConfiguration>false</serviceConfiguration>
  <simpleConversionEnabled>false</simpleConversionEnabled>
  <cqlFilter>age &gt; 365 AND age &lt;= 730</cqlFilter>
  <maxFeatures>0</maxFeatures>
  <numDecimals>0</numDecimals>
  <padWithZeros>false</padWithZeros>
  <forcedDecimal>false</forcedDecimal>
  <overridingServiceSRS>false</overridingServiceSRS>
  <skipNumberMatched>false</skipNumberMatched>
  <circularArcPresent>false</circularArcPresent>
</featureType>